vibedeck/__init__.py
vibedeck/broadcasting.py
vibedeck/config.py
vibedeck/export.py
vibedeck/models.py
vibedeck/permissions.py
vibedeck/pricing.yaml
vibedeck/rendering.py
vibedeck/search.py
vibedeck/secrets.py
vibedeck/server.py
vibedeck/sessions.py
vibedeck/tailer.py
vibedeck/backends/CLAUDE.md
vibedeck/backends/README.md
vibedeck/backends/__init__.py
vibedeck/backends/base.py
vibedeck/backends/multi.py
vibedeck/backends/protocol.py
vibedeck/backends/registry.py
vibedeck/backends/thinking.py
vibedeck/backends/claude_code/__init__.py
vibedeck/backends/claude_code/backend.py
vibedeck/backends/claude_code/cli.py
vibedeck/backends/claude_code/discovery.py
vibedeck/backends/claude_code/pricing.py
vibedeck/backends/claude_code/renderer.py
vibedeck/backends/claude_code/tailer.py
vibedeck/backends/opencode/__init__.py
vibedeck/backends/opencode/backend.py
vibedeck/backends/opencode/cli.py
vibedeck/backends/opencode/discovery.py
vibedeck/backends/opencode/pricing.py
vibedeck/backends/opencode/renderer.py
vibedeck/backends/opencode/tailer.py
vibedeck/backends/shared/__init__.py
vibedeck/backends/shared/rendering.py
vibedeck/routes/__init__.py
vibedeck/routes/archives.py
vibedeck/routes/diff.py
vibedeck/routes/files.py
vibedeck/routes/sessions.py
vibedeck/routes/statuses.py
vibedeck/static/script.js
vibedeck/static/style.css
vibedeck/summarizer/__init__.py
vibedeck/summarizer/config.py
vibedeck/summarizer/generator.py
vibedeck/summarizer/output.py
vibedeck/summarizer/tracker.py
vibedeck/templates/CLAUDE.md
vibedeck/templates/live.html
vibedeck/templates/macros.html
vibedeck/templates/export/base.html
vibedeck/templates/export/index.html
vibedeck/templates/export/page.html
vibedeck/templates/export/search.js
vibedeck/templates/static/js/app.js
vibedeck/templates/static/js/artifacts.js
vibedeck/templates/static/js/commands.js
vibedeck/templates/static/js/connection.js
vibedeck/templates/static/js/diff.js
vibedeck/templates/static/js/filetree.js
vibedeck-0.1.1.dist-info/METADATA
vibedeck-0.1.1.dist-info/WHEEL
vibedeck-0.1.1.dist-info/entry_points.txt
vibedeck-0.1.1.dist-info/licenses/LICENSE
vibedeck-0.1.1.dist-info/RECORD
