Metadata-Version: 2.4
Name: vibedeck
Version: 0.1.1
Summary: Live-updating transcript viewer, web frontend and tooling for Claude Code and OpenCode sessions
Author-email: Tijs Zwinkels <tijs@tinkertank.eu>
License-Expression: Apache-2.0
License-File: LICENSE
Requires-Python: >=3.10
Requires-Dist: click-default-group>=1.2.0
Requires-Dist: click>=8.1.0
Requires-Dist: fastapi>=0.109.0
Requires-Dist: jinja2>=3.1.0
Requires-Dist: markdown>=3.5.0
Requires-Dist: pyyaml>=6.0.0
Requires-Dist: sse-starlette>=2.0.0
Requires-Dist: tomli>=2.0.0; python_version < '3.11'
Requires-Dist: uvicorn>=0.27.0
Requires-Dist: watchfiles>=0.21.0
Provides-Extra: dev
Requires-Dist: black>=24.0.0; extra == 'dev'
Requires-Dist: httpx>=0.27.0; extra == 'dev'
Requires-Dist: pytest-asyncio>=0.23.0; extra == 'dev'
Requires-Dist: pytest>=7.0.0; extra == 'dev'
